junglescout/__init__.py
junglescout/client.py
junglescout/client_async.py
junglescout/client_sync.py
junglescout/exceptions.py
junglescout/models/__init__.py
junglescout/models/default_if_none.py
junglescout/models/parameters/__init__.py
junglescout/models/parameters/api_type.py
junglescout/models/parameters/attributes.py
junglescout/models/parameters/filter_options.py
junglescout/models/parameters/marketplace.py
junglescout/models/parameters/params.py
junglescout/models/parameters/product_filter_options.py
junglescout/models/parameters/product_sort.py
junglescout/models/parameters/product_tiers.py
junglescout/models/parameters/seller_types.py
junglescout/models/parameters/sort.py
junglescout/models/requests/__init__.py
junglescout/models/requests/historical_search_volume_request.py
junglescout/models/requests/keyword_by_asin_request.py
junglescout/models/requests/keywords_by_keyword_request.py
junglescout/models/requests/method.py
junglescout/models/requests/product_database_request.py
junglescout/models/requests/request.py
junglescout/models/requests/sales_estimates_request.py
junglescout/models/requests/share_of_voice_request.py
junglescout/models/responses/__init__.py
junglescout/models/responses/api_response.py
junglescout/models/responses/historical_search_volume.py
junglescout/models/responses/keyword_by_asin.py
junglescout/models/responses/keyword_by_keyword.py
junglescout/models/responses/product_database.py
junglescout/models/responses/sales_estimates.py
junglescout/models/responses/serializer_helpers.py
junglescout/models/responses/share_of_voice.py
junglescout/session.py
junglescout_client-0.6.0.dist-info/METADATA
junglescout_client-0.6.0.dist-info/WHEEL
junglescout_client-0.6.0.dist-info/licenses/LICENSE.txt
junglescout_client-0.6.0.dist-info/RECORD
