Metadata-Version: 2.4
Name: junglescout-client
Version: 0.6.0
Summary: Jungle Scout API Client
License: MIT
License-File: LICENSE.txt
Author: Jungle Scout
Author-email: support@junglescout.com
Requires-Python: >=3.9,<4.0
Classifier: License :: OSI Approved :: MIT License
Classifier: Programming Language :: Python :: 3
Classifier: Programming Language :: Python :: 3.9
Classifier: Programming Language :: Python :: 3.10
Classifier: Programming Language :: Python :: 3.11
Classifier: Programming Language :: Python :: 3.12
Classifier: Programming Language :: Python :: 3.13
Classifier: Programming Language :: Python :: 3.14
Requires-Dist: httpx (>=0.27.2,<0.28.0)
Requires-Dist: pydantic (>=2.6.3,<3.0.0)
Requires-Dist: python-dateutil (>=2.8.2,<3.0.0)
Project-URL: Documentation, https://python-client.junglescout.com
Project-URL: Homepage, https://developer.junglescout.com/api
Project-URL: Issues, https://github.com/Junglescout/junglescout-python-client/issues
Project-URL: Postman Collection, https://postman.junglescout.com/
Project-URL: Repository, https://github.com/Junglescout/junglescout-python-client.git
